firebird/uuid/__about__.py
firebird/uuid/__init__.py
firebird/uuid/_model.py
firebird/uuid/_registry.py
firebird/uuid/_spec.py
firebird_uuid-1.0.0.dist-info/METADATA
firebird_uuid-1.0.0.dist-info/WHEEL
firebird_uuid-1.0.0.dist-info/licenses/LICENSE
firebird_uuid-1.0.0.dist-info/RECORD
