Metadata-Version: 2.4
Name: firebird-uuid
Version: 1.0.0
Summary: Official tools for working with OID namespace managed by the Firebird Project.
Project-URL: Home, https://github.com/FirebirdSQL/firebird-uuid
Project-URL: Documentation, https://firebird-uuid.rtfd.io
Project-URL: Issues, https://github.com/FirebirdSQL/firebird-uuid/issues
Project-URL: Funding, https://github.com/sponsors/pcisar
Project-URL: Source, https://github.com/FirebirdSQL/firebird-uuid/python
Author-email: Pavel Cisar <pcisar@users.sourceforge.net>
License: MIT License
License-File: LICENSE
Keywords: Firebird,UUID
Classifier: Development Status :: 5 - Production/Stable
Classifier: Intended Audience :: Developers
Classifier: License :: OSI Approved :: MIT License
Classifier: Operating System :: MacOS
Classifier: Operating System :: Microsoft :: Windows
Classifier: Operating System :: POSIX :: Linux
Classifier: Programming Language :: Python :: 3 :: Only
Classifier: Programming Language :: Python :: 3.11
Classifier: Programming Language :: Python :: 3.12
Classifier: Programming Language :: Python :: 3.13
Classifier: Programming Language :: Python :: Implementation :: CPython
Classifier: Programming Language :: Python :: Implementation :: PyPy
Classifier: Topic :: Software Development
Classifier: Topic :: Software Development :: Libraries
Requires-Python: <4,>=3.11
Requires-Dist: firebird-base~=2.0
Requires-Dist: pyyaml~=6.0
Requires-Dist: requests~=2.31
Requires-Dist: tomli-w>=1.2
